pic_rucio_policy_package/__init__.py
pic_rucio_policy_package/_version.py
pic_rucio_policy_package/permission.py
pic_rucio_policy_package/schema.py
pic_rucio_policy_package-0.1.1.dist-info/METADATA
pic_rucio_policy_package-0.1.1.dist-info/WHEEL
pic_rucio_policy_package-0.1.1.dist-info/top_level.txt
pic_rucio_policy_package-0.1.1.dist-info/RECORD
