Metadata-Version: 2.4
Name: pic_rucio_policy_package
Version: 0.1.1
Summary: PIC Rucio policy package
Author-email: Francesc Torradeflot <torradeflot@pic.es>
License-Expression: Apache-2.0
Classifier: Programming Language :: Python :: 3
Classifier: Operating System :: OS Independent
Requires-Python: >=3.9
Provides-Extra: dev
Requires-Dist: rucio>=35.5.0; extra == "dev"
Requires-Dist: ruff; extra == "dev"
Requires-Dist: ruff-lsp; extra == "dev"
Requires-Dist: pre-commit; extra == "dev"
Requires-Dist: pytest; extra == "dev"
